mitoedit/__init__.py
mitoedit/cli.py
mitoedit/core.py
mitoedit/pipelines/Cho_sTALEDs.py
mitoedit/pipelines/Mok2020_unified.py
mitoedit/pipelines/README.md
mitoedit/pipelines/__init__.py
mitoedit/pipelines/base_pipeline.py
mitoedit/pipelines/mok2020_base_pipeline.py
mitoedit/resources/__init__.py
mitoedit/resources/mito.txt
mitoedit/talent_tools/README.md
mitoedit/talent_tools/__init__.py
mitoedit/talent_tools/celeryconfig.py
mitoedit/talent_tools/entrez_cache.py
mitoedit/talent_tools/findPairedRvdTALs.py
mitoedit/talent_tools/findRvdTAL.py
mitoedit/talent_tools/findSingleTALsite.py
mitoedit/talent_tools/findTAL.py
mitoedit/talent_tools/findTAL_old.py
mitoedit/talent_tools/re_dict_dump
mitoedit/talent_tools/talconfig.py
mitoedit/talent_tools/talutil.py
mitoedit/talent_tools/utils/re_dict_builder.py
mitoedit/talent_tools/utils/seq_data_updater.py
mitoedit/talent_tools/utils/sequence_versions_dump
mitoedit/web/main.py
mitoedit/web/static/.gitkeep
mitoedit/web/templates/about.html
mitoedit/web/templates/footer.html
mitoedit/web/templates/index.html
mitoedit/web/templates/login.html
mitoedit-1.0.0.dist-info/licenses/LICENSE
mitoedit-1.0.0.dist-info/METADATA
mitoedit-1.0.0.dist-info/WHEEL
mitoedit-1.0.0.dist-info/entry_points.txt
mitoedit-1.0.0.dist-info/top_level.txt
mitoedit-1.0.0.dist-info/RECORD
