Metadata-Version: 2.4
Name: mitoedit
Version: 1.0.0
Summary: A tool for targeted mitochondrial base editing
Author-email: Xun Zhu <Xun.Zhu@stjude.org>, Devansh Shah <Devansh.Shah@stjude.org>
Project-URL: Homepage, https://github.com/Kundu-Lab/mitoedit
Project-URL: Bug Reports, https://github.com/Kundu-Lab/mitoedit/issues
Project-URL: Source, https://github.com/Kundu-Lab/mitoedit
Project-URL: Documentation, https://github.com/Kundu-Lab/mitoedit/blob/main/README.md
Keywords: bioinformatics,mitochondrial,dna,base editing,crispr,tale
Classifier: Development Status :: 4 - Beta
Classifier: Intended Audience :: Science/Research
Classifier: Topic :: Scientific/Engineering :: Bio-Informatics
Classifier: Programming Language :: Python :: 3
Classifier: Programming Language :: Python :: 3.8
Classifier: Programming Language :: Python :: 3.9
Classifier: Programming Language :: Python :: 3.10
Classifier: Programming Language :: Python :: 3.11
Classifier: Programming Language :: Python :: 3.12
Classifier: Operating System :: OS Independent
Requires-Python: >=3.8
License-File: LICENSE
Requires-Dist: pandas>=2.0.0
Provides-Extra: web
Requires-Dist: fastapi>=0.100.0; extra == "web"
Requires-Dist: uvicorn>=0.20.0; extra == "web"
Requires-Dist: python-multipart>=0.0.5; extra == "web"
Requires-Dist: jinja2>=3.0.0; extra == "web"
Provides-Extra: dev
Requires-Dist: pytest>=6.0; extra == "dev"
Requires-Dist: pytest-cov>=2.0; extra == "dev"
Requires-Dist: black>=22.0; extra == "dev"
Requires-Dist: flake8>=4.0; extra == "dev"
Dynamic: license-file
